CollabAgents/__init__.py
CollabAgents/agent.py
CollabAgents/helper.py
CollabAgents/memory.py
CollabAgents/models.py
CollabAgents/tools/AgenticTools.py
CollabAgents/tools/FileOperationsTool.py
CollabAgents/tools/JupyterTool.py
CollabAgents/tools/PythonTool.py
CollabAgents/tools/TerminalTool.py
CollabAgents/tools/__init__.py
CollabAgents/utils/__init__.py
CollabAgents/utils/email_service.py
CollabAgents/utils/query_generator.py
CollabAgents/utils/sql_connectors.py
CollabAgents/utils/vectorestores.py
CollabAgents/utils/web_scraping_service.py
CollabAgents-0.0.6.dist-info/LICENSE.txt
CollabAgents-0.0.6.dist-info/METADATA
CollabAgents-0.0.6.dist-info/WHEEL
CollabAgents-0.0.6.dist-info/top_level.txt
CollabAgents-0.0.6.dist-info/RECORD
