Metadata-Version: 2.1
Name: CollabAgents
Version: 0.0.6
Summary: CollabAgents is a Python framework developed by Vishnu D. for developing AI agents equipped with specialized roles and tools to handle complex user requests efficiently. Users have 100 percent control over their prompts.
Author: Vishnu.D
Author-email: vishnujune17@gmail.com
License: MIT
Keywords: pip install CollabAgents,pip install collabagents
Classifier: Development Status :: 3 - Alpha
Classifier: Intended Audience :: Developers
Classifier: Topic :: Software Development :: Build Tools
Classifier: License :: OSI Approved :: MIT License
Classifier: Programming Language :: Python :: 3.12
License-File: LICENSE.txt
Requires-Dist: instructor ==1.3.4
Requires-Dist: openai ==1.40.1
Requires-Dist: anthropic ==0.34.1
Requires-Dist: pandas ==2.2.2
Requires-Dist: pydantic ==2.8.2
Requires-Dist: pybase64 ==1.4.0
Requires-Dist: requests ==2.32.3
Requires-Dist: tiktoken ==0.7.0
Requires-Dist: websocket-client ==1.8.0
Requires-Dist: lxml ==5.3.0
Requires-Dist: pytest-playwright ==0.5.1
Requires-Dist: scikit-learn ==1.5.1
Requires-Dist: statsmodels ==0.14.2
Requires-Dist: scipy ==1.14.1
Requires-Dist: transformers ==4.44.2
Requires-Dist: notebook ==7.2.1
Requires-Dist: beautifulsoup4 ==4.12.3
Requires-Dist: openpyxl ==3.1.5
Requires-Dist: xlrd ==2.0.1
Requires-Dist: pyodbc ==5.1.0
Requires-Dist: matplotlib ==3.9.2
Requires-Dist: seaborn ==0.13.2
Requires-Dist: plotly ==5.23.0
Requires-Dist: kaleido ==0.2.1
Requires-Dist: chromadb ==0.5.5
Requires-Dist: semantic-text-splitter ==0.15.0
Requires-Dist: markdownify ==0.13.1
Requires-Dist: sentence-transformers ==3.0.1
Requires-Dist: Markdown ==3.7
Requires-Dist: nest-asyncio ==1.6.0
